pysimepar/__init__.py
pysimepar-0.4.dist-info/licenses/LICENSE
pysimepar-0.4.dist-info/METADATA
pysimepar-0.4.dist-info/WHEEL
pysimepar-0.4.dist-info/top_level.txt
pysimepar-0.4.dist-info/RECORD
