Metadata-Version: 2.4
Name: pysimepar
Version: 0.4
Summary: A python package to retrieve forecast data from SIMEPAR
Home-page: https://github.com/clyra/pysimepar
Author: Christian Lyra
Author-email: poplyra@gmail.com
Project-URL: Bug Tracker, https://github.com/clyra/pysimepar/issues
Classifier: Programming Language :: Python :: 3
Classifier: License :: OSI Approved :: MIT License
Classifier: Operating System :: OS Independent
Requires-Python: >=3.6
License-File: LICENSE
Requires-Dist: requests
Requires-Dist: bs4
Dynamic: license-file
